pandas_shredder/__init__.py
pandas_shredder/shredder.py
pandas_shredder/component/__init__.py
pandas_shredder/component/error.py
pandas_shredder/component/validator.py
pandas_shredder-0.0.3.dist-info/LICENSE
pandas_shredder-0.0.3.dist-info/METADATA
pandas_shredder-0.0.3.dist-info/WHEEL
pandas_shredder-0.0.3.dist-info/top_level.txt
pandas_shredder-0.0.3.dist-info/RECORD
