Metadata-Version: 2.1
Name: pandas_shredder
Version: 0.0.3
Summary: Измельчитель для Pandas DataFrame. Позволяет нарезать набор данных на файлы с фиксированным количеством строк
Author-email: Dmitriy Peskov <dv.peskov@yandex.ru>
Project-URL: Homepage, https://github.com/Dmitry-Peskov/pandas-shredder
Project-URL: Issues, https://github.com/Dmitry-Peskov/pandas-shredder/issues
Keywords: pandas,dataframe,shredder,slice,slicer
Classifier: Programming Language :: Python :: 3
Classifier: License :: OSI Approved :: MIT License
Classifier: Development Status :: 5 - Production/Stable
Requires-Python: >=3.11
License-File: LICENSE
Requires-Dist: pandas>=2.2.3
Requires-Dist: openpyxl>=3.1.5
